microcord/__init__.py
microcord-1.0.0.dist-info/LICENSE
microcord-1.0.0.dist-info/WHEEL
microcord-1.0.0.dist-info/METADATA
microcord-1.0.0.dist-info/RECORD
